xkits_config.py
xkits_config_annot.py
xkits_config_attrs.py
xkits_config_class.py
xkits_config_file.py
xkits_config_json.py
xkits_config_toml.py
xkits_config_toml-0.1.dist-info/LICENSE
xkits_config_toml-0.1.dist-info/METADATA
xkits_config_toml-0.1.dist-info/WHEEL
xkits_config_toml-0.1.dist-info/top_level.txt
xkits_config_toml-0.1.dist-info/zip-safe
xkits_config_toml-0.1.dist-info/RECORD
