Metadata-Version: 2.1
Name: xkits-config-toml
Version: 0.1
Summary: Config module
Home-page: https://github.com/bondbox/xconfig/
Author: Mingzhe Zou
Author-email: zoumingzhe@outlook.com
License: GPLv2
Project-URL: Source Code, https://github.com/bondbox/xconfig/
Project-URL: Bug Tracker, https://github.com/bondbox/xconfig/issues
Project-URL: Documentation, https://github.com/bondbox/xconfig/
Keywords: config,configuration
Platform: any
Classifier: Programming Language :: Python
Classifier: Programming Language :: Python :: 3
Requires-Python: >=3.8
License-File: LICENSE
Requires-Dist: xkits-config-file >=0.1
Requires-Dist: toml
